SurvSet/__init__.py
SurvSet/__main__.py
SurvSet/data.py
SurvSet/_datagen/__init__.py
SurvSet/_datagen/__main__.py
SurvSet/_datagen/download_custom.py
SurvSet/_datagen/download_pkgs.py
SurvSet/_datagen/process_datasets.py
SurvSet/_datagen/qc_check.py
SurvSet/_datagen/Cprocess/__init__.py
SurvSet/_datagen/Cprocess/datasets.py
SurvSet/_datagen/Rprocess/__init__.py
SurvSet/_datagen/Rprocess/datasets.py
SurvSet/resources/pickles/AML_Bull.pickle
SurvSet/resources/pickles/Aids2.pickle
SurvSet/resources/pickles/Bergamaschi.pickle
SurvSet/resources/pickles/DBCD.pickle
SurvSet/resources/pickles/DLBCL.pickle
SurvSet/resources/pickles/Dialysis.pickle
SurvSet/resources/pickles/FRTCS.pickle
SurvSet/resources/pickles/Framingham.pickle
SurvSet/resources/pickles/GBSG2.pickle
SurvSet/resources/pickles/LeukSurv.pickle
SurvSet/resources/pickles/MCLcleaned.pickle
SurvSet/resources/pickles/Melanoma.pickle
SurvSet/resources/pickles/NSBCD.pickle
SurvSet/resources/pickles/Pbc3.pickle
SurvSet/resources/pickles/Rossi.pickle
SurvSet/resources/pickles/TRACE.pickle
SurvSet/resources/pickles/UnempDur.pickle
SurvSet/resources/pickles/Unemployment.pickle
SurvSet/resources/pickles/Z243.pickle
SurvSet/resources/pickles/acath.pickle
SurvSet/resources/pickles/actg.pickle
SurvSet/resources/pickles/aids.pickle
SurvSet/resources/pickles/breast.pickle
SurvSet/resources/pickles/burn.pickle
SurvSet/resources/pickles/cancer.pickle
SurvSet/resources/pickles/cgd.pickle
SurvSet/resources/pickles/chop.pickle
SurvSet/resources/pickles/colon.pickle
SurvSet/resources/pickles/cost.pickle
SurvSet/resources/pickles/csl.pickle
SurvSet/resources/pickles/d.oropha.rec.pickle
SurvSet/resources/pickles/dataDIVAT1.pickle
SurvSet/resources/pickles/dataDIVAT2.pickle
SurvSet/resources/pickles/dataDIVAT3.pickle
SurvSet/resources/pickles/dataOvarian1.pickle
SurvSet/resources/pickles/df_ds.csv
SurvSet/resources/pickles/diabetes.pickle
SurvSet/resources/pickles/divorce.pickle
SurvSet/resources/pickles/e1684.pickle
survset-0.2.9.dist-info/METADATA
survset-0.2.9.dist-info/WHEEL
survset-0.2.9.dist-info/top_level.txt
survset-0.2.9.dist-info/RECORD
